{
  "model_name": "linear",
  "model_type": "LinearRegression",
  "performance": {
    "test_r2": 0.791482520928183,
    "test_rmse": 1.292173555510382,
    "test_mae": 0.949205195597259,
    "cv_r2_mean": 0.7977791153727282,
    "cv_r2_std": 0.022677476078571974
  },
  "training_info": {
    "train_samples": 799,
    "test_samples": 200,
    "features": 15,
    "feature_names": [
      "mean_bond_length",
      "std_bond_length",
      "n_bonds",
      "mean_coordination",
      "std_coordination",
      "max_coordination",
      "radius_of_gyration",
      "asphericity",
      "surface_fraction",
      "x_range",
      "y_range",
      "z_range",
      "anisotropy",
      "compactness",
      "bond_variance"
    ]
  },
  "hyperparameters": {}
}